LICENSE
README.md
setup.cfg
setup.py
cloud/__init__.py
cloud/adls/__init__.py
cloud/adls/adls.py
cloud/core/__init__.py
cloud/core/core.py
cloud/gcsfs/__init__.py
cloud/gcsfs/gcsfs.py
cloud/local/__init__.py
cloud/local/local.py
cloud_arrow.egg-info/PKG-INFO
cloud_arrow.egg-info/SOURCES.txt
cloud_arrow.egg-info/dependency_links.txt
cloud_arrow.egg-info/requires.txt
cloud_arrow.egg-info/top_level.txt