Metadata-Version: 2.1
Name: cloud-arrow
Version: 0.8.1
Summary: Python library to provide an Unified cloud storage API for reading and writing parquet and  deltalake files from/to the main cloud provider's object storage using the arrow format
Home-page: https://github.com/a24lorie/Cloud-Arrow
Author-email: a24lorie@gmail.com, nachorodriguez79@gmail.com
License: GNU
License-File: LICENSE
Requires-Dist: pyarrow
Requires-Dist: pandas
Requires-Dist: numpy
Requires-Dist: saspy
Requires-Dist: adlfs
Requires-Dist: gcsfs
Requires-Dist: s3fs
Requires-Dist: azure-identity
Requires-Dist: fsspec
Requires-Dist: deltalake
